tests/__init__.py
tornado_jsonschema/__init__.py
tornado_jsonschema-0.1.0.dist-info/LICENSE
tornado_jsonschema-0.1.0.dist-info/METADATA
tornado_jsonschema-0.1.0.dist-info/WHEEL
tornado_jsonschema-0.1.0.dist-info/top_level.txt
tornado_jsonschema-0.1.0.dist-info/RECORD
